{
   "agent": "SwiftWebSocket",
   "behavior": "OK",
   "behaviorClose": "OK",
   "case": 368,
   "closedByMe": true,
   "createStats": true,
   "createWirelog": true,
   "description": "Send 1000 compressed messages each of payload size 65536, auto-fragment to 0 octets. Use default permessage-deflate offer.",
   "droppedByMe": true,
   "duration": 2216,
   "expectation": "Receive echo'ed messages (with payload as sent). Timeout case after 480 secs.",
   "expected": {},
   "expectedClose": {
      "closeCode": [
         1000
      ],
      "closedByMe": true,
      "requireClean": true
   },
   "failedByMe": false,
   "httpRequest": "GET /runCase?case=368&agent=SwiftWebSocket HTTP/1.1\r\nSec-WebSocket-Extensions: permessage-deflate; client_max_window_bits; server_max_window_bits=15\r\nUpgrade: websocket\r\nUser-Agent: SwiftWebSocket\r\nOrigin: ws://localhost:9001/runCase?case=368&agent=SwiftWebSocket\r\nSec-WebSocket-Version: 13\r\nConnection: Upgrade\r\nHost: localhost:9001\r\nSec-WebSocket-Key: RPg7X1+l5d8RHxl94ZJemw==\r\n\r\n",
   "httpResponse": "HTTP/1.1 101 Switching Protocols\r\nServer: AutobahnTestSuite/0.7.2-0.10.9\r\nX-Powered-By: AutobahnPython/0.10.9\r\nUpgrade: WebSocket\r\nConnection: Upgrade\r\nSec-WebSocket-Accept: QWjJaYGWFA4n8yRR8IxHui6KdYw=\r\nSec-WebSocket-Extensions: permessage-deflate; server_max_window_bits=15\r\n\r\n",
   "id": "12.4.9",
   "isServer": true,
   "localCloseCode": 1000,
   "localCloseReason": null,
   "received": [],
   "remoteCloseCode": null,
   "remoteCloseReason": null,
   "reportCompressionRatio": true,
   "reportTime": true,
   "result": "Ok, received all echo'ed messages in time.",
   "resultClose": "Connection was properly closed",
   "rxFrameStats": {
      "1": 1000,
      "8": 1
   },
   "rxOctetStats": {
      "6": 1,
      "14": 1000,
      "382": 1,
      "65536": 1000
   },
   "started": "2016-04-13T16:14:03.604Z",
   "trafficStats": {
      "incomingCompressionRatio": 1.0,
      "incomingOctetsAppLevel": 65536000,
      "incomingOctetsWebSocketLevel": 65536000,
      "incomingOctetsWireLevel": 65550000,
      "incomingWebSocketFrames": 1000,
      "incomingWebSocketMessages": 1000,
      "incomingWebSocketOverhead": 0.000213623046875,
      "outgoingCompressionRatio": 0.0547767333984375,
      "outgoingOctetsAppLevel": 65536000,
      "outgoingOctetsWebSocketLevel": 3589848,
      "outgoingOctetsWireLevel": 3593848,
      "outgoingWebSocketFrames": 1000,
      "outgoingWebSocketMessages": 1000,
      "outgoingWebSocketOverhead": 0.0011142533054324306,
      "preopenIncomingOctetsWireLevel": 382,
      "preopenOutgoingOctetsWireLevel": 279
   },
   "txFrameStats": {
      "1": 1000,
      "8": 1
   },
   "txOctetStats": {
      "4": 1,
      "279": 1,
      "2576": 1,
      "2578": 1,
      "2582": 1,
      "2587": 1,
      "2590": 1,
      "2591": 1,
      "2593": 1,
      "2595": 2,
      "2596": 3,
      "2598": 1,
      "2599": 4,
      "2600": 1,
      "2601": 3,
      "2602": 1,
      "2603": 1,
      "2604": 5,
      "2605": 1,
      "2606": 1,
      "2607": 5,
      "2608": 2,
      "2609": 2,
      "2610": 3,
      "2613": 2,
      "2614": 5,
      "2615": 3,
      "2616": 3,
      "2617": 1,
      "2618": 2,
      "2619": 2,
      "2620": 3,
      "2622": 3,
      "2623": 1,
      "2625": 3,
      "2626": 1,
      "2627": 1,
      "2628": 2,
      "2629": 3,
      "2630": 2,
      "2631": 3,
      "2632": 1,
      "2633": 1,
      "2634": 2,
      "2635": 2,
      "2636": 2,
      "2637": 3,
      "2639": 1,
      "2640": 1,
      "2641": 1,
      "2642": 1,
      "2644": 2,
      "2645": 5,
      "2646": 2,
      "2649": 1,
      "2650": 1,
      "2666": 1,
      "2668": 1,
      "2673": 2,
      "2674": 2,
      "2676": 1,
      "2677": 1,
      "2680": 1,
      "2683": 1,
      "2684": 1,
      "2685": 1,
      "2686": 2,
      "2688": 1,
      "2691": 1,
      "2693": 2,
      "2694": 1,
      "2700": 2,
      "2701": 1,
      "2702": 2,
      "2711": 1,
      "2713": 2,
      "2721": 1,
      "2722": 1,
      "2724": 1,
      "2727": 2,
      "2728": 2,
      "2729": 1,
      "2730": 2,
      "2731": 2,
      "2734": 1,
      "2736": 1,
      "2738": 1,
      "2739": 1,
      "2740": 2,
      "2741": 1,
      "2742": 1,
      "2743": 1,
      "2744": 2,
      "2745": 1,
      "2746": 1,
      "2747": 1,
      "2748": 1,
      "2750": 3,
      "2752": 1,
      "2753": 1,
      "2754": 1,
      "2755": 1,
      "2756": 2,
      "2757": 3,
      "2758": 2,
      "2759": 2,
      "2761": 2,
      "2762": 2,
      "2763": 3,
      "2764": 3,
      "2765": 5,
      "2766": 3,
      "2767": 2,
      "2768": 6,
      "2770": 3,
      "2771": 1,
      "2772": 3,
      "2773": 6,
      "2774": 1,
      "2778": 1,
      "2779": 3,
      "2780": 2,
      "2781": 1,
      "2782": 1,
      "2784": 2,
      "2785": 2,
      "2786": 1,
      "2787": 1,
      "2788": 1,
      "2789": 1,
      "2790": 1,
      "2792": 4,
      "2793": 4,
      "2795": 3,
      "2796": 2,
      "2797": 1,
      "2798": 1,
      "2800": 2,
      "2802": 1,
      "2803": 2,
      "2804": 1,
      "2807": 2,
      "2808": 1,
      "2809": 2,
      "2810": 4,
      "2813": 1,
      "2814": 1,
      "2816": 1,
      "2817": 2,
      "2818": 1,
      "2821": 2,
      "2822": 4,
      "2823": 2,
      "2824": 2,
      "2825": 1,
      "2826": 2,
      "2827": 3,
      "2828": 2,
      "2829": 1,
      "2830": 1,
      "2831": 4,
      "2833": 3,
      "2835": 1,
      "2843": 1,
      "2846": 2,
      "2847": 1,
      "2851": 1,
      "2852": 1,
      "2854": 1,
      "2855": 2,
      "2857": 1,
      "2863": 1,
      "2865": 2,
      "2866": 1,
      "2870": 1,
      "2872": 1,
      "2873": 2,
      "2876": 1,
      "2877": 1,
      "2878": 1,
      "2891": 1,
      "2893": 1,
      "2894": 2,
      "2898": 3,
      "2904": 1,
      "2906": 1,
      "2908": 1,
      "2909": 1,
      "2910": 1,
      "2913": 1,
      "2918": 1,
      "2925": 2,
      "2933": 1,
      "2939": 1,
      "2942": 2,
      "2959": 3,
      "2965": 1,
      "2967": 1,
      "2968": 1,
      "2969": 1,
      "2972": 1,
      "2978": 1,
      "2980": 1,
      "2982": 1,
      "2983": 2,
      "2984": 1,
      "2985": 1,
      "2989": 1,
      "2995": 1,
      "2996": 1,
      "3002": 1,
      "3004": 1,
      "3008": 1,
      "3010": 1,
      "3016": 1,
      "3020": 1,
      "3027": 1,
      "3030": 1,
      "3031": 1,
      "3034": 1,
      "3037": 1,
      "3040": 1,
      "3095": 1,
      "3100": 1,
      "3107": 1,
      "3112": 1,
      "3118": 1,
      "3150": 1,
      "3153": 1,
      "3156": 1,
      "3158": 1,
      "3178": 1,
      "3179": 1,
      "3183": 1,
      "3187": 1,
      "3188": 1,
      "3189": 2,
      "3190": 1,
      "3191": 2,
      "3192": 1,
      "3193": 1,
      "3195": 2,
      "3204": 1,
      "3205": 1,
      "3206": 1,
      "3208": 2,
      "3209": 3,
      "3211": 2,
      "3216": 1,
      "3219": 1,
      "3220": 1,
      "3221": 1,
      "3222": 2,
      "3223": 1,
      "3224": 1,
      "3226": 2,
      "3227": 1,
      "3228": 1,
      "3232": 1,
      "3234": 1,
      "3235": 1,
      "3236": 3,
      "3238": 1,
      "3250": 1,
      "3251": 1,
      "3253": 1,
      "3256": 1,
      "3264": 1,
      "3268": 1,
      "3269": 1,
      "3270": 1,
      "3272": 1,
      "3280": 1,
      "3300": 1,
      "3301": 1,
      "3304": 1,
      "3306": 1,
      "3307": 1,
      "3315": 1,
      "3317": 1,
      "3339": 1,
      "3340": 1,
      "3349": 2,
      "3350": 1,
      "3353": 2,
      "3358": 1,
      "3381": 1,
      "3386": 1,
      "3389": 1,
      "3392": 1,
      "3393": 1,
      "3395": 2,
      "3397": 2,
      "3406": 1,
      "3407": 1,
      "3409": 2,
      "3410": 1,
      "3411": 1,
      "3414": 2,
      "3415": 1,
      "3416": 1,
      "3420": 1,
      "3421": 1,
      "3426": 1,
      "3427": 1,
      "3434": 1,
      "3436": 2,
      "3439": 1,
      "3446": 2,
      "3468": 1,
      "3470": 1,
      "3474": 1,
      "3479": 1,
      "3480": 1,
      "3483": 1,
      "3490": 1,
      "3491": 1,
      "3493": 1,
      "3494": 1,
      "3495": 1,
      "3503": 1,
      "3510": 1,
      "3514": 2,
      "3518": 1,
      "3521": 1,
      "3529": 1,
      "3530": 1,
      "3549": 1,
      "3557": 1,
      "3563": 2,
      "3572": 1,
      "3580": 1,
      "3592": 1,
      "3606": 1,
      "3624": 1,
      "3625": 1,
      "3626": 1,
      "3631": 1,
      "3640": 1,
      "3641": 1,
      "3646": 1,
      "3648": 1,
      "3650": 2,
      "3651": 1,
      "3653": 1,
      "3659": 3,
      "3668": 1,
      "3669": 1,
      "3693": 1,
      "3696": 2,
      "3700": 1,
      "3701": 1,
      "3702": 3,
      "3703": 2,
      "3705": 2,
      "3707": 1,
      "3710": 2,
      "3715": 1,
      "3716": 1,
      "3718": 2,
      "3719": 1,
      "3720": 1,
      "3722": 1,
      "3726": 2,
      "3728": 3,
      "3729": 1,
      "3731": 1,
      "3733": 1,
      "3737": 1,
      "3738": 2,
      "3739": 2,
      "3740": 1,
      "3741": 1,
      "3743": 1,
      "3744": 1,
      "3745": 1,
      "3755": 1,
      "3779": 1,
      "3780": 1,
      "3781": 2,
      "3782": 1,
      "3786": 1,
      "3787": 2,
      "3788": 2,
      "3789": 1,
      "3790": 1,
      "3791": 1,
      "3792": 1,
      "3793": 1,
      "3796": 1,
      "3797": 1,
      "3798": 3,
      "3804": 1,
      "3810": 1,
      "3821": 1,
      "3828": 1,
      "3840": 1,
      "3841": 1,
      "3866": 1,
      "3909": 1,
      "3915": 1,
      "3916": 2,
      "3926": 1,
      "3936": 1,
      "3939": 1,
      "3940": 1,
      "3942": 1,
      "3951": 1,
      "3960": 1,
      "3981": 1,
      "3982": 1,
      "3983": 1,
      "3985": 1,
      "3987": 1,
      "3988": 1,
      "3989": 1,
      "3991": 1,
      "3994": 3,
      "3995": 1,
      "3998": 1,
      "4003": 1,
      "4008": 1,
      "4009": 1,
      "4014": 1,
      "4026": 2,
      "4027": 2,
      "4029": 2,
      "4030": 2,
      "4032": 1,
      "4034": 1,
      "4036": 1,
      "4045": 1,
      "4046": 1,
      "4054": 1,
      "4055": 1,
      "4101": 1,
      "4120": 1,
      "4138": 1,
      "4152": 1,
      "4163": 1,
      "4164": 1,
      "4174": 2,
      "4176": 1,
      "4181": 1,
      "4209": 2,
      "4235": 1,
      "4240": 1,
      "4256": 1,
      "4266": 1,
      "4270": 2,
      "4277": 1,
      "4280": 1,
      "4282": 1,
      "4284": 1,
      "4290": 1,
      "4292": 2,
      "4293": 1,
      "4294": 1,
      "4296": 1,
      "4298": 3,
      "4301": 3,
      "4302": 2,
      "4303": 1,
      "4304": 1,
      "4307": 1,
      "4308": 2,
      "4311": 1,
      "4313": 1,
      "4314": 1,
      "4321": 2,
      "4322": 1,
      "4323": 1,
      "4325": 2,
      "4327": 2,
      "4328": 1,
      "4329": 1,
      "4330": 1,
      "4331": 1,
      "4332": 1,
      "4334": 1,
      "4340": 1,
      "4341": 1,
      "4342": 3,
      "4343": 1,
      "4346": 1,
      "4347": 1,
      "4349": 1,
      "4352": 2,
      "4354": 2,
      "4355": 1,
      "4357": 1,
      "4359": 3,
      "4360": 2,
      "4362": 1,
      "4367": 1,
      "4368": 1,
      "4369": 3,
      "4370": 1,
      "4372": 2,
      "4373": 2,
      "4374": 1,
      "4375": 3,
      "4376": 1,
      "4378": 3,
      "4379": 6,
      "4380": 3,
      "4381": 1,
      "4382": 1,
      "4383": 1,
      "4384": 1,
      "4386": 3,
      "4387": 2,
      "4388": 7,
      "4389": 3,
      "4390": 1,
      "4391": 1,
      "4392": 2,
      "4393": 2,
      "4394": 3,
      "4397": 2,
      "4398": 3,
      "4399": 1,
      "4400": 2,
      "4401": 1,
      "4402": 1,
      "4403": 4,
      "4405": 2,
      "4406": 4,
      "4407": 3,
      "4408": 3,
      "4409": 1,
      "4410": 1,
      "4411": 2,
      "4412": 2,
      "4413": 4,
      "4414": 1,
      "4416": 4,
      "4418": 1,
      "4419": 1,
      "4420": 1,
      "4421": 1,
      "4422": 3,
      "4423": 1,
      "4424": 1,
      "4425": 2,
      "4427": 1,
      "4428": 2,
      "4429": 4,
      "4430": 3,
      "4431": 3,
      "4432": 1,
      "4433": 1,
      "4434": 2,
      "4435": 2,
      "4436": 1,
      "4437": 1,
      "4438": 3,
      "4440": 3,
      "4441": 2,
      "4442": 1,
      "4443": 6,
      "4445": 2,
      "4446": 1,
      "4447": 2,
      "4449": 2,
      "4451": 1,
      "4454": 1,
      "4458": 4,
      "4459": 1,
      "4460": 2,
      "4463": 1,
      "4464": 1,
      "4465": 1,
      "4466": 2,
      "4467": 1,
      "4468": 2,
      "4472": 2,
      "4477": 1,
      "4480": 1,
      "4484": 1,
      "4486": 1,
      "4487": 1,
      "4489": 1,
      "4491": 4,
      "4496": 1,
      "4497": 2,
      "4501": 2,
      "4506": 2,
      "4507": 2,
      "4510": 2,
      "4511": 1,
      "4512": 1,
      "4514": 1,
      "4517": 1,
      "4518": 1,
      "4520": 1,
      "4522": 2,
      "4523": 1,
      "4524": 1,
      "4527": 1,
      "4528": 3,
      "4533": 2,
      "4537": 2,
      "4538": 1,
      "4539": 1,
      "4540": 2,
      "4542": 2,
      "4544": 1,
      "4546": 2,
      "4557": 1,
      "4571": 1,
      "4575": 1,
      "4577": 1,
      "4578": 2,
      "4580": 1,
      "4582": 1,
      "4585": 1,
      "4592": 1,
      "4607": 1,
      "4619": 1,
      "4622": 1,
      "4624": 1,
      "4626": 2,
      "4627": 1,
      "4633": 1,
      "4634": 1,
      "4635": 1,
      "4646": 1,
      "4653": 2,
      "4658": 1,
      "4660": 1,
      "4661": 1,
      "4663": 1,
      "4664": 2,
      "4673": 1,
      "4674": 1,
      "4675": 1,
      "4677": 1,
      "4681": 2,
      "4685": 1,
      "4687": 2,
      "4688": 1,
      "4690": 2,
      "4694": 1,
      "4696": 1,
      "4698": 3,
      "4699": 1,
      "4702": 2,
      "4703": 2,
      "4704": 2,
      "4708": 1,
      "4717": 1,
      "4718": 1,
      "4719": 2,
      "4720": 2,
      "4721": 1,
      "4722": 1,
      "4723": 2,
      "4724": 3,
      "4725": 2,
      "4726": 1,
      "4728": 1,
      "4729": 1,
      "4730": 1
   },
   "wasClean": true,
   "wasCloseHandshakeTimeout": false,
   "wasNotCleanReason": null,
   "wasOpenHandshakeTimeout": false,
   "wasServerConnectionDropTimeout": false,
   "wirelog": [
      [
         "RO",
         [
            382,
            "474554202f72756e436173653f636173653d333638266167656e743d5377696674576562536f636b657420485454502f312e310d0a5365632d576562536f636b ..."
         ]
      ],
      [
         "TO",
         [
            279,
            "485454502f312e312031303120537769746368696e672050726f746f636f6c730d0a5365727665723a204175746f6261686e5465737453756974652f302e372e ..."
         ],
         false
      ],
      [
         "WLM",
         false
      ],
      [
         "TI",
         480
      ],
      [
         "WLM",
         true
      ],
      [
         "TF",
         [
            2,
            "0x03e8"
         ],
         8,
         true,
         0,
         null,
         null,
         null,
         false
      ],
      [
         "TO",
         [
            4,
            "880203e8"
         ],
         false
      ],
      [
         "RO",
         [
            6,
            "88806af767a6"
         ]
      ],
      [
         "RF",
         [
            0,
            ""
         ],
         8,
         true,
         0,
         true,
         "6af767a6"
      ]
   ]
}