{
   "agent": "SwiftWebSocket",
   "behavior": "OK",
   "behaviorClose": "OK",
   "case": 348,
   "closedByMe": true,
   "createStats": true,
   "createWirelog": true,
   "description": "Send 1000 compressed messages each of payload size 16384, auto-fragment to 0 octets. Use default permessage-deflate offer.",
   "droppedByMe": true,
   "duration": 1701,
   "expectation": "Receive echo'ed messages (with payload as sent). Timeout case after 480 secs.",
   "expected": {},
   "expectedClose": {
      "closeCode": [
         1000
      ],
      "closedByMe": true,
      "requireClean": true
   },
   "failedByMe": false,
   "httpRequest": "GET /runCase?case=348&agent=SwiftWebSocket HTTP/1.1\r\nUser-Agent: SwiftWebSocket\r\nSec-WebSocket-Version: 13\r\nUpgrade: websocket\r\nConnection: Upgrade\r\nHost: localhost:9001\r\nOrigin: ws://localhost:9001/runCase?case=348&agent=SwiftWebSocket\r\nSec-WebSocket-Key: GZKtDjExtc02Ue+HrRNETg==\r\nSec-WebSocket-Extensions: permessage-deflate; client_max_window_bits; server_max_window_bits=15\r\n\r\n",
   "httpResponse": "HTTP/1.1 101 Switching Protocols\r\nServer: AutobahnTestSuite/0.7.1-0.10.4\r\nX-Powered-By: AutobahnPython/0.10.4\r\nUpgrade: WebSocket\r\nConnection: Upgrade\r\nSec-WebSocket-Accept: gIVgnVuAKWjtKVZEQgb0UPggy2s=\r\nSec-WebSocket-Extensions: permessage-deflate; server_max_window_bits=15\r\n\r\n",
   "id": "12.3.7",
   "isServer": true,
   "localCloseCode": 1000,
   "localCloseReason": null,
   "received": [],
   "remoteCloseCode": null,
   "remoteCloseReason": null,
   "reportCompressionRatio": true,
   "reportTime": true,
   "result": "Ok, received all echo'ed messages in time.",
   "resultClose": "Connection was properly closed",
   "rxFrameStats": {
      "2": 1000,
      "8": 1
   },
   "rxOctetStats": {
      "6": 1,
      "8": 16,
      "52": 1,
      "382": 1,
      "16340": 1,
      "16384": 16,
      "16392": 983
   },
   "started": "2015-05-26T20:33:50.071Z",
   "trafficStats": {
      "incomingCompressionRatio": 1.0,
      "incomingOctetsAppLevel": 16384000,
      "incomingOctetsWebSocketLevel": 16384000,
      "incomingOctetsWireLevel": 16392000,
      "incomingWebSocketFrames": 1000,
      "incomingWebSocketMessages": 1000,
      "incomingWebSocketOverhead": 0.00048828125,
      "outgoingCompressionRatio": 0.37820556640625,
      "outgoingOctetsAppLevel": 16384000,
      "outgoingOctetsWebSocketLevel": 6196520,
      "outgoingOctetsWireLevel": 6200520,
      "outgoingWebSocketFrames": 1000,
      "outgoingWebSocketMessages": 1000,
      "outgoingWebSocketOverhead": 0.000645523616481509,
      "preopenIncomingOctetsWireLevel": 382,
      "preopenOutgoingOctetsWireLevel": 279
   },
   "txFrameStats": {
      "2": 1000,
      "8": 1
   },
   "txOctetStats": {
      "4": 1,
      "279": 1,
      "5504": 1,
      "5536": 1,
      "5558": 1,
      "5570": 1,
      "5577": 1,
      "5593": 1,
      "5595": 1,
      "5598": 1,
      "5600": 1,
      "5602": 1,
      "5604": 1,
      "5610": 1,
      "5616": 1,
      "5629": 1,
      "5635": 1,
      "5644": 1,
      "5658": 1,
      "5664": 1,
      "5671": 1,
      "5695": 1,
      "5697": 1,
      "5700": 1,
      "5715": 1,
      "5735": 2,
      "5769": 1,
      "5771": 1,
      "5782": 1,
      "5792": 1,
      "5798": 1,
      "5808": 1,
      "5809": 1,
      "5818": 1,
      "5819": 1,
      "5820": 1,
      "5825": 1,
      "5829": 1,
      "5840": 1,
      "5843": 1,
      "5850": 1,
      "5856": 1,
      "5857": 1,
      "5859": 1,
      "5861": 1,
      "5863": 1,
      "5866": 1,
      "5868": 1,
      "5869": 2,
      "5872": 1,
      "5873": 1,
      "5875": 1,
      "5885": 1,
      "5887": 1,
      "5888": 2,
      "5889": 1,
      "5893": 2,
      "5895": 3,
      "5896": 1,
      "5897": 1,
      "5899": 1,
      "5900": 1,
      "5901": 2,
      "5902": 2,
      "5904": 2,
      "5905": 2,
      "5907": 3,
      "5909": 3,
      "5913": 2,
      "5914": 4,
      "5916": 1,
      "5918": 1,
      "5921": 1,
      "5923": 1,
      "5924": 1,
      "5925": 2,
      "5927": 1,
      "5928": 1,
      "5929": 3,
      "5931": 2,
      "5933": 2,
      "5934": 1,
      "5936": 3,
      "5937": 2,
      "5938": 1,
      "5940": 5,
      "5941": 1,
      "5942": 2,
      "5943": 3,
      "5944": 4,
      "5946": 1,
      "5947": 1,
      "5948": 2,
      "5949": 5,
      "5950": 3,
      "5951": 2,
      "5953": 2,
      "5955": 2,
      "5956": 1,
      "5958": 1,
      "5960": 3,
      "5963": 1,
      "5964": 4,
      "5965": 1,
      "5967": 2,
      "5968": 1,
      "5969": 2,
      "5970": 1,
      "5971": 2,
      "5972": 2,
      "5973": 1,
      "5974": 2,
      "5975": 3,
      "5977": 1,
      "5979": 3,
      "5981": 1,
      "5982": 1,
      "5983": 2,
      "5984": 1,
      "5985": 2,
      "5986": 2,
      "5988": 4,
      "5990": 2,
      "5991": 4,
      "5992": 2,
      "5993": 4,
      "5994": 2,
      "5995": 2,
      "5997": 3,
      "5998": 1,
      "5999": 5,
      "6000": 1,
      "6001": 4,
      "6003": 2,
      "6004": 1,
      "6005": 1,
      "6006": 2,
      "6007": 2,
      "6008": 3,
      "6009": 3,
      "6010": 2,
      "6011": 3,
      "6012": 1,
      "6013": 1,
      "6014": 1,
      "6016": 3,
      "6017": 1,
      "6018": 1,
      "6019": 1,
      "6020": 3,
      "6022": 2,
      "6023": 4,
      "6024": 2,
      "6025": 2,
      "6026": 1,
      "6027": 2,
      "6028": 2,
      "6029": 3,
      "6031": 1,
      "6032": 1,
      "6033": 5,
      "6034": 4,
      "6035": 2,
      "6036": 1,
      "6037": 2,
      "6038": 2,
      "6040": 1,
      "6043": 1,
      "6044": 1,
      "6045": 4,
      "6046": 2,
      "6047": 1,
      "6048": 2,
      "6049": 2,
      "6050": 1,
      "6051": 2,
      "6052": 1,
      "6053": 1,
      "6054": 5,
      "6055": 2,
      "6056": 2,
      "6057": 2,
      "6058": 3,
      "6059": 2,
      "6060": 3,
      "6061": 3,
      "6062": 6,
      "6063": 3,
      "6064": 5,
      "6065": 4,
      "6066": 3,
      "6067": 3,
      "6068": 1,
      "6069": 3,
      "6070": 2,
      "6071": 3,
      "6072": 2,
      "6074": 2,
      "6075": 1,
      "6076": 1,
      "6077": 3,
      "6078": 4,
      "6079": 4,
      "6080": 3,
      "6081": 1,
      "6082": 2,
      "6083": 2,
      "6085": 2,
      "6087": 2,
      "6088": 2,
      "6089": 4,
      "6091": 2,
      "6093": 1,
      "6095": 1,
      "6096": 1,
      "6097": 2,
      "6099": 1,
      "6101": 2,
      "6102": 2,
      "6104": 1,
      "6105": 1,
      "6108": 4,
      "6109": 2,
      "6110": 1,
      "6111": 1,
      "6112": 2,
      "6113": 1,
      "6114": 1,
      "6115": 2,
      "6117": 1,
      "6118": 1,
      "6120": 1,
      "6121": 1,
      "6122": 1,
      "6123": 2,
      "6124": 1,
      "6126": 1,
      "6128": 2,
      "6130": 2,
      "6132": 1,
      "6134": 2,
      "6136": 1,
      "6139": 2,
      "6140": 2,
      "6141": 1,
      "6143": 2,
      "6144": 3,
      "6145": 1,
      "6147": 1,
      "6148": 2,
      "6149": 1,
      "6150": 1,
      "6153": 3,
      "6154": 3,
      "6156": 1,
      "6158": 3,
      "6159": 1,
      "6161": 1,
      "6162": 4,
      "6163": 2,
      "6164": 1,
      "6165": 2,
      "6166": 1,
      "6167": 1,
      "6168": 2,
      "6169": 3,
      "6170": 2,
      "6171": 3,
      "6172": 1,
      "6173": 1,
      "6176": 2,
      "6177": 3,
      "6178": 2,
      "6179": 3,
      "6180": 2,
      "6182": 1,
      "6183": 2,
      "6184": 2,
      "6185": 3,
      "6186": 3,
      "6187": 2,
      "6188": 2,
      "6189": 3,
      "6191": 3,
      "6192": 2,
      "6193": 3,
      "6194": 3,
      "6195": 3,
      "6197": 2,
      "6199": 1,
      "6200": 2,
      "6201": 3,
      "6202": 2,
      "6203": 4,
      "6205": 2,
      "6206": 1,
      "6207": 3,
      "6208": 6,
      "6210": 2,
      "6211": 1,
      "6213": 4,
      "6214": 2,
      "6216": 1,
      "6217": 1,
      "6218": 1,
      "6219": 3,
      "6220": 1,
      "6221": 1,
      "6222": 1,
      "6231": 1,
      "6236": 2,
      "6238": 1,
      "6239": 1,
      "6240": 1,
      "6242": 1,
      "6247": 1,
      "6249": 1,
      "6253": 1,
      "6256": 1,
      "6260": 2,
      "6268": 3,
      "6272": 2,
      "6278": 1,
      "6281": 1,
      "6283": 3,
      "6286": 1,
      "6288": 1,
      "6290": 1,
      "6292": 2,
      "6293": 1,
      "6294": 1,
      "6298": 2,
      "6299": 4,
      "6300": 1,
      "6302": 5,
      "6303": 2,
      "6305": 2,
      "6306": 2,
      "6307": 1,
      "6308": 2,
      "6310": 3,
      "6311": 5,
      "6312": 2,
      "6313": 4,
      "6315": 1,
      "6316": 1,
      "6319": 3,
      "6320": 1,
      "6321": 3,
      "6322": 2,
      "6323": 2,
      "6324": 3,
      "6325": 1,
      "6326": 1,
      "6327": 2,
      "6328": 2,
      "6331": 1,
      "6332": 1,
      "6336": 6,
      "6337": 2,
      "6338": 1,
      "6341": 3,
      "6342": 3,
      "6343": 1,
      "6344": 2,
      "6345": 1,
      "6346": 2,
      "6347": 2,
      "6348": 2,
      "6349": 2,
      "6350": 1,
      "6351": 2,
      "6352": 1,
      "6353": 2,
      "6356": 1,
      "6357": 2,
      "6359": 4,
      "6360": 3,
      "6361": 3,
      "6363": 3,
      "6364": 2,
      "6365": 2,
      "6366": 2,
      "6367": 5,
      "6368": 4,
      "6369": 3,
      "6370": 3,
      "6371": 3,
      "6372": 3,
      "6373": 4,
      "6374": 2,
      "6375": 4,
      "6376": 3,
      "6378": 1,
      "6379": 2,
      "6380": 3,
      "6381": 4,
      "6382": 4,
      "6383": 3,
      "6384": 4,
      "6385": 5,
      "6386": 5,
      "6387": 1,
      "6388": 5,
      "6389": 4,
      "6390": 4,
      "6391": 6,
      "6392": 3,
      "6393": 6,
      "6394": 3,
      "6395": 2,
      "6396": 3,
      "6397": 3,
      "6398": 1,
      "6399": 1,
      "6400": 3,
      "6401": 3,
      "6402": 2,
      "6403": 3,
      "6404": 1,
      "6405": 1,
      "6408": 1,
      "6410": 3,
      "6411": 2,
      "6412": 2,
      "6413": 1,
      "6414": 1,
      "6415": 1,
      "6420": 2,
      "6422": 2,
      "6423": 3,
      "6424": 1,
      "6425": 1,
      "6428": 2,
      "6431": 1,
      "6440": 1,
      "6441": 1,
      "6442": 1,
      "6443": 1,
      "6446": 2,
      "6447": 2,
      "6448": 1,
      "6449": 1,
      "6450": 1,
      "6460": 2,
      "6461": 1,
      "6466": 1,
      "6468": 1,
      "6471": 1,
      "6474": 1,
      "6475": 1,
      "6476": 2,
      "6477": 1,
      "6478": 2,
      "6479": 2,
      "6480": 2,
      "6483": 1,
      "6485": 1,
      "6486": 2,
      "6488": 1,
      "6489": 1,
      "6490": 4,
      "6491": 2,
      "6496": 1,
      "6497": 2,
      "6498": 1,
      "6502": 1,
      "6503": 1,
      "6504": 1,
      "6505": 2,
      "6506": 4,
      "6507": 1,
      "6508": 2,
      "6510": 1,
      "6512": 1,
      "6514": 1,
      "6517": 1,
      "6518": 1,
      "6519": 1,
      "6522": 1,
      "6528": 1,
      "6536": 1,
      "6549": 1,
      "6550": 1,
      "6568": 1,
      "6571": 1,
      "6577": 1,
      "6579": 1,
      "6585": 1,
      "6587": 1,
      "6594": 2,
      "6595": 1,
      "6596": 1,
      "6597": 1,
      "6598": 1,
      "6606": 1,
      "6618": 1,
      "6625": 1,
      "6634": 1,
      "6636": 1,
      "6644": 1,
      "6647": 1,
      "6653": 1,
      "6655": 2,
      "6656": 1,
      "6660": 1,
      "6661": 3,
      "6662": 1,
      "6664": 3,
      "6666": 1,
      "6667": 1,
      "6669": 1,
      "6671": 1,
      "6673": 1,
      "6674": 1,
      "6681": 1,
      "6683": 1,
      "6688": 1,
      "6694": 1,
      "6699": 1,
      "6700": 1,
      "6701": 1,
      "6704": 1,
      "6706": 1,
      "6707": 1,
      "6716": 1,
      "6717": 2,
      "6733": 1,
      "6749": 1,
      "6752": 1,
      "6761": 1,
      "6763": 1,
      "6769": 1,
      "6775": 1,
      "6778": 1,
      "6791": 1,
      "6797": 1,
      "6818": 1,
      "6827": 1,
      "6830": 1,
      "6838": 1,
      "6849": 1,
      "6855": 1,
      "6864": 1,
      "6871": 1,
      "6886": 1,
      "7247": 1
   },
   "wasClean": true,
   "wasCloseHandshakeTimeout": false,
   "wasNotCleanReason": null,
   "wasOpenHandshakeTimeout": false,
   "wasServerConnectionDropTimeout": false,
   "wirelog": [
      [
         "RO",
         [
            382,
            "474554202f72756e436173653f636173653d333438266167656e743d5377696674576562536f636b657420485454502f312e310d0a557365722d4167656e743a ..."
         ]
      ],
      [
         "TO",
         [
            279,
            "485454502f312e312031303120537769746368696e672050726f746f636f6c730d0a5365727665723a204175746f6261686e5465737453756974652f302e372e ..."
         ],
         false
      ],
      [
         "WLM",
         false
      ],
      [
         "TI",
         480
      ],
      [
         "WLM",
         true
      ],
      [
         "TF",
         [
            2,
            "0x03e8"
         ],
         8,
         true,
         0,
         null,
         null,
         null,
         false
      ],
      [
         "TO",
         [
            4,
            "880203e8"
         ],
         false
      ],
      [
         "RO",
         [
            6,
            "88804a26d006"
         ]
      ],
      [
         "RF",
         [
            0,
            ""
         ],
         8,
         true,
         0,
         true,
         "4a26d006"
      ]
   ]
}